mpl_interact/__init__.py
mpl_interact/__version__.py
mpl_interact/base.py
mpl_interact/drag.py
mpl_interact/shortcut.py
mpl_interact/state.py
mpl_interact/utils.py
mpl_interact/zoom.py
mpl_interact-0.0.1.dist-info/LICENSE
mpl_interact-0.0.1.dist-info/METADATA
mpl_interact-0.0.1.dist-info/WHEEL
mpl_interact-0.0.1.dist-info/top_level.txt
mpl_interact-0.0.1.dist-info/RECORD
